{
  "underlined_newstitle" : "eireli_empresa_individual_de_responsabilidade_limitada_e_tema_no_saber_direito_parte_ii",

  "newstitle"   : "EIRELI: Empresa Individual de Responsabilidade Limitada é tema no Saber Direito (Parte 2 de 2)",

  "subtitle"    : "O tradicional programa de videocursos televisivos da TV Justiça traz um novo conjunto de cinco aulas sobre a EIRELI, ié, a Empresa Individual de Responsabilidade Limitada.",

  "description" : "Nesta segunda parte, continuaremos e concluiremos a visão de conjunto do videocurso do Programa 'Saber Direito', originalmente televisionado na semana do dia 25 de dezembro 2017, intitulado: 'EIRELI: Empresa Individual de Responsabilidade Limitada' e ministrado pela professora Juliana Palú.",

  "related_sabdircursos": ["2017-12-25","2010-07-19"]
}
