{
  "underlined_newstitle" : "tributacao_na_propriedade_no_acervo_de_videocursos_do_saber_direito_parte_i",
  "newstitle"   : "Tributação na Propriedade no acervo de videocursos do Saber Direito (Parte 1 de 3)",
  "subtitle"    : "Segundo argumenta o prof. Pedro Bonifácio, em paráfrase: a tributação realiza a 'solidariedade social', na qual a capacidade contributiva dos contribuintes permite, por meio das receitas derivadas geradas, a viabilidade do Estado e seus serviços sociais.",
  "description" : "O tradicional programa televisivo 'Saber Direito', da semana do dia 8 de janeiro, 2018, recebe o especialista e mestrando em Direito Tributário, o professor Pedro Bonifácio. O videocurso abordará, entre outros, os seguintes aspectos da Tributação sobre a Propriedade: [1] obrigação tributária, [2] propriedade urbana e rural, [3] princípios e imunidades na propriedade, [4] responsabilidade tributária na propriedade e [5] tributação na transmissão da propriedade.",

  "related_sabdircursos": ["2018-01-08","2011-06-27"]
}
