{
  "underlined_newstitle" : "o_direito_ao_juri_em_materias_civis_nos_eua_parte_i",
  "newstitle"   : "O Direito ao Júri em Matérias Civis nos EUA (Parte 1 de 3)",
  "subtitle"    : "Em um Ordenamento Jurídico de mundo 'Civil Law', como o nosso, de repente olhar para 'fora' e ver que no Ordenamento Jurídico Estadunidense existe o júri civil, parece uma interessante, talvez quase surpreendente, experiência em Direito Comparativo.",
  "description" : "Neste artigo, investigamos a situação da 'preservação' do júri civil, pelo menos em jurisdição federal, nos EUA, em vistas às mudanças de contexto para este antigo direito, incluindo o fato de o Reino Unido, o próprio criador do direito ao júri civil, tê-lo abolido modernamente.",
  "related_sabdircursos": ["2016-06-20","2011-06-13"]
}
